shapes/___init__.py
shapes/__main__.py
shapes/interpreter.py
shapes/parser.py
shapes/shape.py
shapes/utils.py
shaapes-0.1.0.dist-info/LICENSE
shaapes-0.1.0.dist-info/WHEEL
shaapes-0.1.0.dist-info/METADATA
shaapes-0.1.0.dist-info/RECORD
