Metadata-Version: 2.1
Name: shaapes
Version: 0.1.0
Summary: A graphical shape based esolang
Home-page: https://github.com/photon-niko/shapes/
License: GPL-3.0
Keywords: shapes,graphical,esoteric,esolang,programming,language,graph,image
Author: Calico Niko
Requires-Python: >=3.9,<3.11
Classifier: License :: OSI Approved :: GNU General Public License v3 (GPLv3)
Classifier: Programming Language :: Python :: 3
Classifier: Programming Language :: Python :: 3.10
Classifier: Programming Language :: Python :: 3.9
Requires-Dist: dotmap (>=1.3.30,<2.0.0)
Requires-Dist: imutils (>=0.5.4,<0.6.0)
Requires-Dist: numpy (>=1.22.3,<2.0.0)
Requires-Dist: opencv-python (>=4.5.5,<5.0.0)
Requires-Dist: scipy (>=1.8.0,<2.0.0)
Project-URL: Repository, https://github.com/photon-niko/shapes/
